calculatorSetupByPythonForTesting/__init__.py
calculatorSetupByPythonForTesting-0.1.dist-info/LICENSE.txt
calculatorSetupByPythonForTesting-0.1.dist-info/METADATA
calculatorSetupByPythonForTesting-0.1.dist-info/WHEEL
calculatorSetupByPythonForTesting-0.1.dist-info/top_level.txt
calculatorSetupByPythonForTesting-0.1.dist-info/RECORD
