Metadata-Version: 2.1
Name: calculatorSetupByPythonForTesting
Version: 0.1
Summary: This is a simple calculator
Home-page: UNKNOWN
Author: Abirami
Author-email: abiramig1930@gmail.com
License: UNKNOWN
Platform: UNKNOWN
Classifier: Programming Language :: Python :: 3
Classifier: License :: OSI Approved :: MIT License
Classifier: Operating System :: OS Independent
License-File: LICENSE.txt
